expatriate/Attribute.py
expatriate/CharacterData.py
expatriate/Comment.py
expatriate/Document.py
expatriate/Element.py
expatriate/Namespace.py
expatriate/Node.py
expatriate/Parent.py
expatriate/ProcessingInstruction.py
expatriate/__init__.py
expatriate/exceptions.py
expatriate/model/AttributeMapper.py
expatriate/model/ContentMapper.py
expatriate/model/ElementMapper.py
expatriate/model/Mapper.py
expatriate/model/Model.py
expatriate/model/__init__.py
expatriate/model/decorators.py
expatriate/model/exceptions.py
expatriate/model/types.py
expatriate/model/xml/__init__.py
expatriate/model/xs/AllNniType.py
expatriate/model/xs/AllType.py
expatriate/model/xs/AnnotatedType.py
expatriate/model/xs/AnnotationElement.py
expatriate/model/xs/AnyElement.py
expatriate/model/xs/AnySimpleType.py
expatriate/model/xs/AnyTypeType.py
expatriate/model/xs/AnyUriType.py
expatriate/model/xs/AppinfoElement.py
expatriate/model/xs/AttributeGroupType.py
expatriate/model/xs/AttributeType.py
expatriate/model/xs/Base64BinaryType.py
expatriate/model/xs/BooleanType.py
expatriate/model/xs/ByteType.py
expatriate/model/xs/ChoiceElement.py
expatriate/model/xs/ComplexContentElement.py
expatriate/model/xs/ComplexTypeType.py
expatriate/model/xs/DateTimeStampType.py
expatriate/model/xs/DateTimeType.py
expatriate/model/xs/DateType.py
expatriate/model/xs/DayTimeDurationType.py
expatriate/model/xs/DecimalType.py
expatriate/model/xs/DocumentationElement.py
expatriate/model/xs/DoubleType.py
expatriate/model/xs/DurationType.py
expatriate/model/xs/ElementType.py
expatriate/model/xs/EntitiesType.py
expatriate/model/xs/EntityType.py
expatriate/model/xs/ExtensionType.py
expatriate/model/xs/FacetType.py
expatriate/model/xs/FieldElement.py
expatriate/model/xs/FieldXPath.py
expatriate/model/xs/FloatType.py
expatriate/model/xs/GDayType.py
expatriate/model/xs/GMonthDayType.py
expatriate/model/xs/GMonthType.py
expatriate/model/xs/GYearMonthType.py
expatriate-0.4.dist-info/DESCRIPTION.rst
expatriate-0.4.dist-info/METADATA
expatriate-0.4.dist-info/RECORD
expatriate-0.4.dist-info/WHEEL
expatriate-0.4.dist-info/metadata.json
expatriate-0.4.dist-info/top_level.txt
expatriate-0.4.dist-info/zip-safe
